thaifin/__init__.py
thaifin/py.typed
thaifin/stock.py
thaifin/stocks.py
thaifin/sources/__init__.py
thaifin/sources/finnomena/__init__.py
thaifin/sources/finnomena/api.py
thaifin/sources/finnomena/model.py
thaifin/sources/finnomena/service.py
thaifin/sources/thai_securities_data/__init__.py
thaifin/sources/thai_securities_data/api.py
thaifin/sources/thai_securities_data/service.py
thaifin/sources/thai_securities_data/models/__init__.py
thaifin/sources/thai_securities_data/models/meta_data.py
thaifin/sources/thai_securities_data/models/securities_data.py
thaifin-1.1.0.dist-info/METADATA
thaifin-1.1.0.dist-info/WHEEL
thaifin-1.1.0.dist-info/licenses/LICENSE.md
thaifin-1.1.0.dist-info/RECORD
