Metadata-Version: 2.4
Name: thaifin
Version: 1.1.0
Summary: A Python library for access thai stock fundamental data up to 10+ years.
Author-email: Nutchanon Ninyawee <me@nutchanon.org>
License: ISC
License-File: LICENSE.md
Requires-Python: >=3.11
Requires-Dist: arrow>=1.3.0
Requires-Dist: beautifulsoup4>=4.12.0
Requires-Dist: cachetools>=5.0.0
Requires-Dist: furl>=2.1.0
Requires-Dist: httpx>=0.27.0
Requires-Dist: ipython>=9.4.0
Requires-Dist: lxml>=5.0.0
Requires-Dist: numpy>=1.24.0
Requires-Dist: pandas-stubs>=2.3.0.250703
Requires-Dist: pandas>=2.0.0
Requires-Dist: pydantic>=2.7.0
Requires-Dist: python-levenshtein>=0.27.1
Requires-Dist: rapidfuzz>=3.13.0
Requires-Dist: requests>=2.31.0
Requires-Dist: ruff>=0.12.4
Requires-Dist: tenacity>=8.0.0
Requires-Dist: types-cachetools>=6.1.0.20250717
Provides-Extra: dev
Requires-Dist: jupyter>=1.0.0; extra == 'dev'
Requires-Dist: lxml>=5.0.0; extra == 'dev'
Requires-Dist: openpyxl>=3.1.0; extra == 'dev'
Requires-Dist: pdoc>=14.0.0; extra == 'dev'
Requires-Dist: pytest>=8.0.0; extra == 'dev'
Requires-Dist: tqdm>=4.60.0; extra == 'dev'
Provides-Extra: full
Requires-Dist: python-levenshtein>=0.25.0; extra == 'full'
